[
  {
    "tipo": "NOTA",
    "numero": "254",
    "fechora": "12-10-22 12:35",
    "title": "Solicitan la compra para la intertribus",
    "docente": "Lic. Maria Perez"
  },
  {
    "tipo": "Exp.",
    "numero": "21054",
    "fechora": "12-10-22 12:35",
    "title": "  Elit est sequi vero illum ducimus Magnam excepturi aperiam omnis nam dicta voluptatum Officiis quasi dolorem velit eligendi asperiores. Iusto aperiam labore at ratione est Omnis laboriosam alias ad nostrum.",
    "docente": "Lic. Maria Perez"
  },
  {
    "tipo": "Exp.",
    "numero": "21365",
    "fechora": "12-10-22 12:35",
    "title": "Solicitan la compra para la intertribus en el acto de redencion",
    "docente": "Lic. Maria Perez"
  },
  {
    "tipo": "Exp.",
    "numero": "21054",
    "fechora": "12-10-22 12:35",
    "title": "  Elit est sequi vero illum ducimus Magnam excepturi aperiam omnis nam dicta voluptatum Officiis quasi dolorem velit eligendi asperiores. Iusto aperiam labore at ratione est Omnis laboriosam alias ad nostrum.",
    "docente": "Lic. Maria Perez"
  }
]
